{"cameraMode":{"drawMode":0,"name":"Shaded","section":"Shading Mode"},"sceneLighting":true,"audioPlay":false,"sceneViewState":{"showFog":true,"showMaterialUpdate":false,"showSkybox":true,"showFlares":true,"showImageEffects":true,"showParticleSystems":true},"in2DMode":false,"pivot":{"x":2.7998852729797365,"y":-9.175926208496094,"z":12.108662605285645},"rotation":{"x":0.405452698469162,"y":0.17978602647781373,"z":-0.0815054178237915,"w":0.8926820158958435},"size":7.966436862945557,"orthographic":false}